Meth5py/__init__.py
Meth5py-0.4.2.dist-info/LICENSE
Meth5py-0.4.2.dist-info/METADATA
Meth5py-0.4.2.dist-info/WHEEL
Meth5py-0.4.2.dist-info/top_level.txt
Meth5py-0.4.2.dist-info/RECORD
