Metadata-Version: 2.1
Name: Meth5py
Version: 0.4.2
Summary: A class for converting BSMAPz methratio output into a fast and compressed hdf5 format
Home-page: https://github.com/zyndagj/Meth5py
Author: Greg Zynda
Author-email: zyndagj@gmail.com
License: BSD
Platform: UNKNOWN
Classifier: License :: OSI Approved :: BSD License
Requires: h5py
Requires: numpy
